create_packet/__init__.py
create_packet/__main__.py
create_packet/create_setup/__init__.py
create_packet/create_setup/create_file.py
create_packet/create_setup/setup_template.py
create_packet_project-0.0.5.dist-info/LICENSE
create_packet_project-0.0.5.dist-info/METADATA
create_packet_project-0.0.5.dist-info/WHEEL
create_packet_project-0.0.5.dist-info/top_level.txt
create_packet_project-0.0.5.dist-info/RECORD
