Metadata-Version: 2.1
Name: create-packet-project
Version: 0.0.5
Summary: 自动生成创建资源包所需要的文件
Home-page: https://gitee.com/jin-yongqing/create_packet.git
Author: jack_jin
Author-email: 2960688709@qq.com
License: UNKNOWN
Platform: UNKNOWN
Classifier: Programming Language :: Python :: 3
Classifier: License :: OSI Approved :: MIT License
Classifier: Operating System :: OS Independent
License-File: LICENSE
